odoo/addons/website_event_require_legal/README.rst
odoo/addons/website_event_require_legal/__init__.py
odoo/addons/website_event_require_legal/__manifest__.py
odoo/addons/website_event_require_legal/controllers/__init__.py
odoo/addons/website_event_require_legal/controllers/main.py
odoo/addons/website_event_require_legal/i18n/es.po
odoo/addons/website_event_require_legal/i18n/it.po
odoo/addons/website_event_require_legal/i18n/website_event_require_legal.pot
odoo/addons/website_event_require_legal/models/__init__.py
odoo/addons/website_event_require_legal/models/event.py
odoo/addons/website_event_require_legal/readme/CONFIGURE.md
odoo/addons/website_event_require_legal/readme/CONTRIBUTORS.md
odoo/addons/website_event_require_legal/readme/DESCRIPTION.md
odoo/addons/website_event_require_legal/readme/USAGE.md
odoo/addons/website_event_require_legal/static/description/icon.png
odoo/addons/website_event_require_legal/static/description/index.html
odoo/addons/website_event_require_legal/static/tests/tours/tour.esm.js
odoo/addons/website_event_require_legal/tests/__init__.py
odoo/addons/website_event_require_legal/tests/test_ui.py
odoo/addons/website_event_require_legal/views/event_templates_page_registration.xml
odoo/addons/website_event_require_legal/views/event_views.xml
odoo_addon_website_event_require_legal-18.0.1.0.0.2.dist-info/METADATA
odoo_addon_website_event_require_legal-18.0.1.0.0.2.dist-info/WHEEL
odoo_addon_website_event_require_legal-18.0.1.0.0.2.dist-info/top_level.txt
odoo_addon_website_event_require_legal-18.0.1.0.0.2.dist-info/RECORD
